slash_help/__init__.py
slash_help/errors.py
slash_help/slash_help.py
slash_help-2.0.5.dist-info/LICENSE
slash_help-2.0.5.dist-info/METADATA
slash_help-2.0.5.dist-info/WHEEL
slash_help-2.0.5.dist-info/top_level.txt
slash_help-2.0.5.dist-info/RECORD
