Metadata-Version: 2.1
Name: slash-help
Version: 2.0.5
Summary: discord-py-interactions slash command help
Home-page: https://github.com/Toricane/slash-help
Author: Toricane
Author-email: prjwl028@gmail.com
License: GNU
Platform: UNKNOWN
Classifier: Programming Language :: Python :: 3
Classifier: Development Status :: 4 - Beta
Classifier: License :: OSI Approved :: GNU General Public License v3 (GPLv3)
Classifier: Operating System :: OS Independent
License-File: LICENSE
Requires-Dist: discord-py-interactions
Requires-Dist: discord.py
Requires-Dist: dinteractions-Paginator
Requires-Dist: thefuzz
Requires-Dist: Levenshtein
